[{"__type__":"cc.ImageAsset","content":{"fmt":"0","w":0,"h":0}},{"__type__":"cc.SpriteFrame","content":{"image":"09y2zN80lK0KsIGIVYn/iH","name":"singleColor","rect":{"x":0,"y":0,"width":2,"height":2},"offset":{"x":0,"y":0},"originalSize":{"width":2,"height":2},"rotated":false,"capInsets":[0,0,0,0]}},{"__type__":"cc.ImageAsset","content":{"fmt":"0","w":0,"h":0}},{"__type__":"cc.ImageAsset","content":{"fmt":"0","w":0,"h":0}},{"__type__":"cc.ImageAsset","content":{"fmt":"0","w":0,"h":0}},{"__type__":"cc.ImageAsset","content":{"fmt":"0","w":0,"h":0}}]
